azuread_aws/amazon.py
azuread_aws/http.py
azuread_aws/azure/__init__.py
azuread_aws/azure/auth.py
azuread_aws/azure/constants.py
azuread_aws/azure/graph_api.py
azuread_aws/commands/app_role.py
azuread_aws/commands/cli.py
azuread_aws/commands/idp.py
azuread_aws/commands/user.py
aad_aws_sso-0.1.1.dist-info/METADATA
aad_aws_sso-0.1.1.dist-info/WHEEL
aad_aws_sso-0.1.1.dist-info/entry_points.txt
aad_aws_sso-0.1.1.dist-info/top_level.txt
aad_aws_sso-0.1.1.dist-info/zip-safe
aad_aws_sso-0.1.1.dist-info/RECORD
