Metadata-Version: 2.1
Name: aad-aws-sso
Version: 0.1.1
Summary: Configure and manage AzureAD Idp and AWS Sp SAML setup for your AWS organization.
Home-page: UNKNOWN
Author: Stanislav Yudin
Author-email: stan@endlessinsomnia.com
License: UNKNOWN
Platform: UNKNOWN
Requires-Python: >=3.6
Requires-Dist: boto3
